{
  "1920": {
    "USA": 35
  },
  "1930": {
    "USA": 716,
    "RUS": 5,
    "FRA": 29,
    "DEU": 20,
    "GBR": 33,
    "CZE": 3,
    "NLD": 3,
    "TUR": 1,
    "JPN": 3,
    "ITA": 14,
    "IND": 2,
    "SWE": 2,
    "POL": 5,
    "ESP": 1,
    "HUN": 3,
    "CHE": 2,
    "AUT": 4,
    "CAN": 1,
    "PSE": 1,
    "AUS": 1,
    "MEX": 1,
    "BEL": 1
  },
  "1940": {
    "USA": 1339,
    "GBR": 67,
    "ITA": 22,
    "ESP": 4,
    "AUT": 4,
    "DEU": 10,
    "CZE": 3,
    "NOR": 1,
    "SWE": 7,
    "HUN": 3,
    "CHE": 7,
    "CAN": 8,
    "FIN": 1,
    "PRT": 1,
    "ROU": 1,
    "RUS": 8,
    "POL": 2,
    "AUS": 2,
    "BEL": 1,
    "NLD": 1,
    "FRA": 16,
    "DNK": 1,
    "MEX": 5,
    "IND": 1
  },
  "1950": {
    "USA": 1083,
    "ITA": 157,
    "GBR": 141,
    "FRA": 152,
    "CAN": 16,
    "MEX": 37,
    "IND": 32,
    "JPN": 55,
    "RUS": 36,
    "SWE": 27,
    "DEU": 66,
    "ESP": 48,
    "BRA": 17,
    "ARG": 17,
    "CHE": 8,
    "NLD": 8,
    "GRC": 10,
    "VEN": 5,
    "HUN": 8,
    "CHN": 2,
    "CZE": 13,
    "POL": 12,
    "NOR": 9,
    "EGY": 11,
    "BEL": 5,
    "AUT": 12,
    "MAR": 3,
    "IRL": 9,
    "HRV": 13,
    "ALB": 4,
    "AUS": 3,
    "CHL": 2,
    "DNK": 9,
    "HKG": 3,
    "BGR": 7,
    "CUB": 1,
    "ISR": 1,
    "LBN": 3,
    "ROU": 5,
    "FIN": 7,
    "TUR": 1,
    "SGP": 1,
    "MYS": 1,
    "LKA": 1,
    "NGA": 1,
    "TUN": 3,
    "IRN": 2,
    "GHA": 1,
    "BGD": 2,
    "PAK": 2,
    "MNG": 2,
    "PRT": 1,
    "IRQ": 1,
    "PRK": 1,
    "VNM": 1,
    "NZL": 1,
    "KOR": 1
  },
  "1960": {
    "USA": 1111,
    "ITA": 224,
    "FRA": 295,
    "RUS": 55,
    "GBR": 275,
    "NLD": 29,
    "BEL": 16,
    "MEX": 29,
    "DEU": 106,
    "PAK": 3,
    "DNK": 28,
    "FIN": 14,
    "ESP": 53,
    "IND": 30,
    "THA": 2,
    "CHE": 23,
    "GRC": 33,
    "ARG": 40,
    "ROU": 19,
    "JPN": 49,
    "AUT": 13,
    "NOR": 15,
    "VNM": 6,
    "CZE": 45,
    "PHL": 1,
    "BGR": 18,
    "HRV": 56,
    "EGY": 13,
    "HKG": 4,
    "POL": 36,
    "BRA": 25,
    "KOR": 6,
    "SWE": 65,
    "LKA": 3,
    "HUN": 26,
    "CHN": 6,
    "PRK": 1,
    "CHL": 4,
    "IDN": 4,
    "IRN": 3,
    "TWN": 1,
    "MNG": 4,
    "LBN": 3,
    "CAN": 33,
    "TUN": 2,
    "VEN": 2,
    "TUR": 5,
    "AUS": 7,
    "CUB": 8,
    "CYP": 1,
    "ISR": 16,
    "PER": 3,
    "SEN": 2,
    "NGA": 1,
    "MAR": 3,
    "COD": 1,
    "LIE": 1,
    "IRL": 3,
    "GAB": 1,
    "PRT": 1,
    "DZA": 6,
    "NZL": 1,
    "ZAF": 2,
    "KHM": 1,
    "ISL": 2,
    "BGD": 1,
    "NER": 2
  },
  "1970": {
    "USA": 1272,
    "MEX": 28,
    "ITA": 186,
    "DEU": 165,
    "FRA": 282,
    "DZA": 23,
    "POL": 32,
    "GBR": 283,
    "CZE": 25,
    "BEL": 30,
    "SWE": 44,
    "IND": 19,
    "CAN": 66,
    "TUN": 5,
    "CHE": 29,
    "ESP": 56,
    "ISR": 23,
    "ARG": 13,
    "CHL": 3,
    "BRA": 24,
    "GRC": 12,
    "JPN": 37,
    "EGY": 8,
    "HUN": 52,
    "HRV": 39,
    "RUS": 61,
    "AUS": 10,
    "NLD": 17,
    "CUB": 19,
    "SEN": 10,
    "SYR": 7,
    "MNG": 7,
    "AUT": 8,
    "ROU": 11,
    "DNK": 17,
    "VNM": 9,
    "IRN": 24,
    "FIN": 7,
    "BGR": 18,
    "NOR": 12,
    "IRL": 5,
    "KOR": 2,
    "BOL": 1,
    "IRQ": 3,
    "PRT": 2,
    "AGO": 2,
    "PER": 7,
    "SAU": 1,
    "MCO": 1,
    "LBN": 4,
    "ZAF": 1,
    "LKA": 2,
    "VEN": 6,
    "THA": 1,
    "MAR": 2,
    "TWN": 2,
    "HKG": 3,
    "NER": 1,
    "COL": 1,
    "PHL": 3,
    "TUR": 5,
    "MRT": 1,
    "NZL": 1,
    "CIV": 1,
    "ISL": 2,
    "LBY": 1,
    "KWT": 1,
    "GHA": 1,
    "BGD": 1,
    "NGA": 1
  },
  "1980": {
    "RUS": 81,
    "GBR": 409,
    "USA": 1631,
    "JPN": 63,
    "POL": 47,
    "FRA": 355,
    "HKG": 15,
    "BEL": 26,
    "HRV": 28,
    "DEU": 240,
    "ITA": 159,
    "SWE": 48,
    "ESP": 53,
    "TUR": 17,
    "FIN": 15,
    "ISR": 16,
    "CAN": 110,
    "DZA": 13,
    "ZAF": 13,
    "BRA": 33,
    "GRC": 20,
    "CZE": 33,
    "CHE": 64,
    "AUT": 23,
    "HUN": 55,
    "BGR": 13,
    "PHL": 3,
    "IND": 32,
    "NLD": 28,
    "MEX": 27,
    "COL": 6,
    "VEN": 5,
    "CUB": 12,
    "ARG": 28,
    "AUS": 49,
    "NZL": 8,
    "NOR": 19,
    "ROU": 7,
    "IRQ": 3,
    "EGY": 5,
    "PER": 5,
    "PRT": 9,
    "SYR": 2,
    "CHN": 28,
    "TUN": 8,
    "IRN": 3,
    "THA": 1,
    "MNG": 4,
    "LIE": 2,
    "NGA": 1,
    "DNK": 19,
    "CMR": 2,
    "LBN": 1,
    "BOL": 1,
    "MTQ": 2,
    "AGO": 1,
    "NIC": 1,
    "CRI": 1,
    "MAR": 1,
    "GIN": 1,
    "SEN": 2,
    "VNM": 2,
    "KOR": 12,
    "IRL": 8,
    "AFG": 2,
    "PRK": 2,
    "BFA": 6,
    "ISL": 1,
    "CIV": 1,
    "LKA": 1,
    "TWN": 2,
    "ANT": 3,
    "CHL": 5,
    "MLI": 4,
    "PSE": 1,
    "ZWE": 8
  },
  "1990": {
    "USA": 2058,
    "JPN": 138,
    "ITA": 250,
    "FRA": 608,
    "RUS": 98,
    "GBR": 506,
    "DEU": 275,
    "ESP": 108,
    "CAN": 131,
    "ARG": 20,
    "POL": 46,
    "BRA": 21,
    "FIN": 19,
    "SWE": 45,
    "IRL": 32,
    "CHE": 85,
    "MEX": 61,
    "CZE": 26,
    "IRN": 21,
    "NLD": 48,
    "HUN": 40,
    "GRC": 17,
    "DNK": 45,
    "NZL": 22,
    "AUS": 65,
    "AUT": 33,
    "CHN": 50,
    "CHL": 4,
    "BFA": 8,
    "COL": 4,
    "BGR": 4,
    "PRI": 1,
    "IND": 9,
    "BEL": 75,
    "HRV": 16,
    "HKG": 55,
    "PRT": 28,
    "TUR": 15,
    "ZAF": 11,
    "MAR": 5,
    "EGY": 4,
    "DZA": 5,
    "NOR": 27,
    "KOR": 13,
    "CUB": 6,
    "ROU": 11,
    "ISR": 17,
    "ISL": 8,
    "SEN": 2,
    "LUX": 11,
    "GEO": 6,
    "TWN": 25,
    "BLR": 1,
    "VNM": 7,
    "MYS": 2,
    "TJK": 5,
    "GHA": 1,
    "HTI": 1,
    "URY": 1,
    "MDA": 1,
    "KHM": 1,
    "MKD": 6,
    "UKR": 3,
    "TUN": 4,
    "GNB": 2,
    "LIE": 1,
    "MLI": 1,
    "SGP": 1,
    "ALB": 4,
    "BIH": 5,
    "KAZ": 5,
    "PSE": 1,
    "IDN": 1,
    "PER": 6,
    "ZWE": 1,
    "SVN": 1,
    "NIC": 3,
    "LBN": 2,
    "CPV": 1,
    "PHL": 2,
    "TCD": 2
  },
  "2000": {
    "USA": 2326,
    "AUS": 117,
    "DEU": 665,
    "ITA": 412,
    "RUS": 110,
    "CAN": 297,
    "JPN": 180,
    "GBR": 665,
    "FRA": 863,
    "CUB": 3,
    "CHN": 97,
    "IRL": 41,
    "UKR": 17,
    "BGR": 16,
    "ESP": 152,
    "CZE": 37,
    "SWE": 81,
    "NOR": 43,
    "DNK": 74,
    "CHE": 80,
    "FIN": 32,
    "ISR": 68,
    "ARG": 63,
    "IRN": 70,
    "TUR": 24,
    "MEX": 78,
    "BEL": 109,
    "TUN": 5,
    "HKG": 74,
    "TWN": 49,
    "KOR": 63,
    "PHL": 19,
    "MAR": 33,
    "NLD": 91,
    "NPL": 1,
    "AUT": 60,
    "ROU": 31,
    "PRT": 29,
    "BRA": 46,
    "POL": 53,
    "UZB": 2,
    "IND": 30,
    "HRV": 16,
    "THA": 15,
    "BIH": 10,
    "SVN": 9,
    "COL": 5,
    "ISL": 10,
    "LTU": 2,
    "GRC": 19,
    "VNM": 5,
    "NZL": 55,
    "HUN": 48,
    "MLT": 15,
    "LUX": 25,
    "BFA": 5,
    "MKD": 7,
    "ALB": 3,
    "DZA": 11,
    "EGY": 6,
    "BGD": 1,
    "GEO": 9,
    "CYP": 4,
    "EST": 5,
    "MRT": 2,
    "MOZ": 1,
    "LVA": 6,
    "KAZ": 4,
    "KGZ": 1,
    "PSE": 6,
    "LBN": 7,
    "ARM": 1,
    "KHM": 1,
    "ZAF": 17,
    "SRB": 4,
    "IDN": 1,
    "ARE": 5,
    "SEN": 4,
    "LIE": 1,
    "URY": 9,
    "AZE": 2,
    "AFG": 6,
    "CHL": 6,
    "VEN": 2,
    "CMR": 4,
    "HTI": 1,
    "SVK": 5,
    "PER": 3,
    "ZMB": 1,
    "RWA": 1,
    "MNG": 1,
    "PRK": 1,
    "IRQ": 3,
    "PAK": 2,
    "LKA": 3,
    "SYR": 2,
    "PRI": 1,
    "ECU": 1,
    "TCD": 6,
    "SGP": 7,
    "PRY": 1,
    "MYS": 5,
    "ETH": 5,
    "IMN": 1,
    "LBR": 1,
    "KWT": 1,
    "JOR": 1
  },
  "2010": {
    "USA": 2460,
    "DEU": 625,
    "GBR": 727,
    "AUS": 157,
    "JPN": 184,
    "IRL": 55,
    "BEL": 246,
    "FRA": 1259,
    "ZAF": 32,
    "NZL": 33,
    "CAN": 271,
    "LVA": 15,
    "POL": 90,
    "KOR": 78,
    "CZE": 44,
    "ARG": 93,
    "ESP": 136,
    "IRQ": 7,
    "NLD": 142,
    "ARE": 37,
    "EGY": 16,
    "PSE": 24,
    "RUS": 132,
    "CHL": 70,
    "MEX": 112,
    "NOR": 74,
    "HUN": 59,
    "AUT": 74,
    "UKR": 24,
    "TWN": 33,
    "GRC": 48,
    "DNK": 117,
    "TUR": 78,
    "ITA": 350,
    "SWE": 136,
    "IND": 120,
    "ZWE": 1,
    "HRV": 34,
    "BRA": 106,
    "IRN": 64,
    "CHE": 124,
    "THA": 18,
    "ROU": 59,
    "DOM": 1,
    "CHN": 232,
    "ISR": 83,
    "HKG": 63,
    "CUB": 4,
    "QAT": 62,
    "SRB": 40,
    "SVN": 15,
    "COL": 21,
    "PER": 11,
    "FIN": 40,
    "TCD": 8,
    "ALB": 12,
    "VEN": 10,
    "BIH": 18,
    "BGR": 34,
    "DZA": 11,
    "TUN": 13,
    "LUX": 23,
    "LTU": 7,
    "URY": 15,
    "GEO": 11,
    "ISL": 15,
    "FJI": 2,
    "LBN": 32,
    "PNG": 1,
    "SVK": 17,
    "PHL": 30,
    "BLR": 6,
    "PAK": 3,
    "PRT": 49,
    "SAU": 9,
    "JOR": 12,
    "SGP": 16,
    "SYR": 8,
    "KAZ": 13,
    "PRI": 3,
    "MAR": 16,
    "SEN": 9,
    "IDN": 20,
    "IMN": 1,
    "MKD": 12,
    "AFG": 9,
    "LKA": 3,
    "EST": 6,
    "TZA": 1,
    "GNB": 4,
    "LAO": 4,
    "MLI": 1,
    "GTM": 12,
    "GHA": 4,
    "AZE": 2,
    "CYP": 6,
    "CIV": 2,
    "KHM": 6,
    "ETH": 6,
    "MYS": 3,
    "UZB": 3,
    "VNM": 4,
    "ECU": 2,
    "FRO": 2,
    "YEM": 1,
    "MNG": 2,
    "COD": 1,
    "ZMB": 2,
    "KGZ": 1,
    "NPL": 2,
    "MNE": 1,
    "MMR": 3,
    "LSO": 1,
    "KEN": 5,
    "BTN": 1,
    "BOL": 1,
    "MRT": 1,
    "NIC": 1,
    "CRI": 5,
    "LBR": 1,
    "BGD": 2,
    "VUT": 1,
    "MLT": 4,
    "MOZ": 1,
    "GIN": 1,
    "RWA": 1,
    "VAT": 1,
    "ARM": 3,
    "PRY": 4,
    "SDN": 3,
    "GRL": 1,
    "MCO": 1
  },
  "2020": {
    "GBR": 294,
    "FRA": 427,
    "USA": 1079,
    "MKD": 8,
    "ESP": 56,
    "KOR": 39,
    "IND": 29,
    "JPN": 69,
    "AUS": 41,
    "ITA": 161,
    "DEU": 232,
    "RUS": 58,
    "NZL": 18,
    "CZE": 26,
    "CHE": 51,
    "BEL": 119,
    "SYR": 3,
    "SRB": 19,
    "NLD": 40,
    "SVN": 12,
    "BIH": 5,
    "CAN": 126,
    "CHN": 73,
    "MEX": 64,
    "COL": 16,
    "POL": 53,
    "TWN": 19,
    "GRC": 20,
    "TUN": 10,
    "DZA": 4,
    "ROU": 32,
    "SWE": 72,
    "BRA": 30,
    "KAZ": 4,
    "AZE": 2,
    "BGR": 17,
    "PRT": 27,
    "MDA": 2,
    "ARG": 30,
    "PHL": 9,
    "LTU": 7,
    "KEN": 1,
    "HRV": 11,
    "CIV": 1,
    "SEN": 6,
    "TUR": 26,
    "QAT": 44,
    "UKR": 7,
    "CHL": 17,
    "IRN": 38,
    "AUT": 27,
    "FIN": 27,
    "DNK": 54,
    "ISR": 16,
    "RWA": 1,
    "MCO": 1,
    "URY": 6,
    "MAR": 12,
    "KHM": 8,
    "HKG": 20,
    "PSE": 2,
    "NGA": 4,
    "NOR": 25,
    "EGY": 17,
    "ZAF": 8,
    "IRL": 24,
    "LUX": 22,
    "VEN": 3,
    "GEO": 5,
    "ISL": 10,
    "PAK": 5,
    "HUN": 28,
    "EST": 7,
    "CYP": 6,
    "LBN": 3,
    "CUB": 1,
    "THA": 6,
    "TCD": 1,
    "HTI": 2,
    "BEN": 3,
    "VNM": 3,
    "YEM": 2,
    "ARE": 5,
    "BOL": 4,
    "JOR": 9,
    "LVA": 4,
    "ALB": 2,
    "SGP": 6,
    "SVK": 8,
    "IRQ": 1,
    "BGD": 1,
    "LKA": 2,
    "PAN": 2,
    "IDN": 4,
    "BTN": 1,
    "CRI": 2,
    "NPL": 4,
    "GHA": 1,
    "SAU": 18,
    "MNG": 5,
    "GRL": 1,
    "SDN": 4,
    "BFA": 1,
    "MLI": 2,
    "DOM": 2,
    "NAM": 2,
    "PER": 1,
    "MRT": 1
  }
}